gcoin/__init__.py
gcoin/deterministic.py
gcoin/main.py
gcoin/py2specials.py
gcoin/py3specials.py
gcoin/ripemd.py
gcoin/script.py
gcoin/special.py
gcoin/transaction.py
gcoin-1.1.47.data/data/LICENSE
gcoin-1.1.47.dist-info/DESCRIPTION.rst
gcoin-1.1.47.dist-info/METADATA
gcoin-1.1.47.dist-info/RECORD
gcoin-1.1.47.dist-info/WHEEL
gcoin-1.1.47.dist-info/metadata.json
gcoin-1.1.47.dist-info/top_level.txt
