Metadata-Version: 2.0
Name: gcoin
Version: 1.1.47
Summary: Python Gcoin Tools
Home-page: UNKNOWN
Author: gcoin
Author-email: developer@diqi.us
License: UNKNOWN
Platform: UNKNOWN
